README.md
setup.py
src/geotoys/__init__.py
src/geotoys/animation.py
src/geotoys/datetime.py
src/geotoys/geotiff.py
src/geotoys/jpeg2000.py
src/geotoys/locate.py
src/geotoys/netcdf.py
src/geotoys/plot.py
src/geotoys/process.py
src/geotoys/sentinel.py
src/geotoys/system.py
src/geotoys/version.py
src/geotoys.egg-info/PKG-INFO
src/geotoys.egg-info/SOURCES.txt
src/geotoys.egg-info/dependency_links.txt
src/geotoys.egg-info/requires.txt
src/geotoys.egg-info/top_level.txt