Metadata-Version: 1.2
Name: geotoys
Version: 0.0.2
Summary: Tools for working with geospatial data in python
Home-page: https://github.com/ryanjdillon/geotoys
Maintainer: Ryan J. Dillon
License: MIT
Platform: UNKNOWN
